ghminer/__init__.py
ghminer/golang/__init__.py
ghminer/golang/gomod.py
ghminer/golang/nameconv.py
ghminer/parser/__init__.py
ghminer/parser/gomod.py
ghminer/parser/parquet.py
ghminer/retriever/__init__.py
ghminer/retriever/commit.py
ghminer/retriever/repository.py
ghminer/utils/__init__.py
ghminer/utils/common.py
ghminer-0.1.8.dist-info/LICENSE
ghminer-0.1.8.dist-info/METADATA
ghminer-0.1.8.dist-info/WHEEL
ghminer-0.1.8.dist-info/top_level.txt
ghminer-0.1.8.dist-info/RECORD
