Metadata-Version: 2.1
Name: ghminer
Version: 0.1.8
Summary: Github mining tool for MSR research
Author-email: Justin Zhang <schnell18@gmail.com>
License: Copyright 2023 Justin Zhang
Project-URL: Homepage, https://github.com/schnell18/ghminer
Classifier: Development Status :: 3 - Alpha
Classifier: Intended Audience :: Developers
Classifier: License :: OSI Approved :: MIT No Attribution License (MIT-0)
Classifier: Programming Language :: Python
Classifier: Programming Language :: Python :: 3
Classifier: Programming Language :: Python :: 3.7
Classifier: Programming Language :: Python :: 3.8
Classifier: Programming Language :: Python :: 3.9
Classifier: Programming Language :: Python :: 3.10
Classifier: Programming Language :: Python :: 3.11
Classifier: Programming Language :: Python :: Implementation :: CPython
Requires-Python: >=3.7
License-File: LICENSE
Requires-Dist: requests ==2.31.0
Requires-Dist: semver ==3.0.1
Requires-Dist: PyGithub ==2.0.1-preview
Requires-Dist: isodate ==0.6.1
Requires-Dist: pandas ==2.0.1
Provides-Extra: dev
Requires-Dist: bumpver ; extra == 'dev'
Requires-Dist: pip-tools ; extra == 'dev'
Provides-Extra: doc
Requires-Dist: sphinx ; extra == 'doc'
Provides-Extra: test
Requires-Dist: tox ; extra == 'test'
